chiapos.cpython-314-x86_64-linux-gnu.so
chiapos.libs/libbladebit_harvester-275612fa.so
chiapos-2.0.12.dist-info/METADATA
chiapos-2.0.12.dist-info/WHEEL
chiapos-2.0.12.dist-info/top_level.txt
chiapos-2.0.12.dist-info/RECORD
chiapos-2.0.12.dist-info/licenses/LICENSE
