Metadata-Version: 2.4
Name: chiapos
Version: 2.0.12
Summary: Chia proof of space plotting, proving, and verifying (wraps C++)
Home-page: https://github.com/Chia-Network/chiapos
Author: Mariano Sorgente
Author-email: mariano@chia.net
License: Apache-2.0
Requires-Python: >=3.7
License-File: LICENSE
Dynamic: author
Dynamic: author-email
Dynamic: description
Dynamic: description-content-type
Dynamic: home-page
Dynamic: license
Dynamic: license-file
Dynamic: requires-python
Dynamic: summary
